extract_numbers/__init__.py
extract_numbers/core.py
extract_numbers-1.0.2.dist-info/licenses/LICENSE
tests/test_core.py
extract_numbers-1.0.2.dist-info/METADATA
extract_numbers-1.0.2.dist-info/WHEEL
extract_numbers-1.0.2.dist-info/top_level.txt
extract_numbers-1.0.2.dist-info/RECORD
