Metadata-Version: 2.4
Name: extract-numbers
Version: 1.0.2
Summary: Extract numbers from strings with support for commas, decimals, negatives, and the European format.
Author-email: Talha Awan <talha@talhaawan.net>
License: MIT
Project-URL: Homepage, https://github.com/talhaawan/extract-numbers
Keywords: extract,get,find,number,numbers,text,string,regex,parser,python
Classifier: Development Status :: 5 - Production/Stable
Classifier: Intended Audience :: Developers
Classifier: Programming Language :: Python :: 3
Classifier: Programming Language :: Python :: 3.8
Classifier: Programming Language :: Python :: 3.9
Classifier: Programming Language :: Python :: 3.10
Classifier: Programming Language :: Python :: 3.11
Classifier: Programming Language :: Python :: 3.12
Classifier: Programming Language :: Python :: 3.13
Classifier: Topic :: Text Processing :: Linguistic
Classifier: Topic :: Software Development :: Libraries :: Python Modules
Requires-Python: >=3.8
License-File: LICENSE
Provides-Extra: dev
Requires-Dist: pytest; extra == "dev"
Requires-Dist: mypy; extra == "dev"
Requires-Dist: ruff; extra == "dev"
Dynamic: license-file
